README.rst
setup.py
src/wellcome_aws_utils/__init__.py
src/wellcome_aws_utils/deployment_utils.py
src/wellcome_aws_utils/dynamo_event.py
src/wellcome_aws_utils/dynamo_utils.py
src/wellcome_aws_utils/ecs_utils.py
src/wellcome_aws_utils/exceptions.py
src/wellcome_aws_utils/lambda_utils.py
src/wellcome_aws_utils/reporting_utils.py
src/wellcome_aws_utils/s3_utils.py
src/wellcome_aws_utils/sns_utils.py
src/wellcome_aws_utils/sqs_utils.py
src/wellcome_aws_utils/version.py
src/wellcome_aws_utils.egg-info/PKG-INFO
src/wellcome_aws_utils.egg-info/SOURCES.txt
src/wellcome_aws_utils.egg-info/dependency_links.txt
src/wellcome_aws_utils.egg-info/requires.txt
src/wellcome_aws_utils.egg-info/top_level.txt