Metadata-Version: 1.2
Name: wellcome-aws-utils
Version: 2.2.0
Summary: A collection of AWS utilities
Home-page: https://github.com/wellcometrust/aws_utils
Author: Wellcome Trust (Digital Platform Team)
Author-email: wellcomedigitalplatform@wellcome.ac.uk
License: UNKNOWN
Keywords: aws
Platform: UNKNOWN
Classifier: Development Status :: 5 - Production/Stable
Classifier: Programming Language :: Python :: 3.6
Classifier: Programming Language :: Python :: 3 :: Only
Classifier: Topic :: Software Development
Classifier: Topic :: Utilities
Requires-Python: >=3.6
